{
  "replace": true,
  "trades": [
    {
      "type": "goblintraders:upgraded_potion",
      "offer_item": {
        "item": "minecraft:potion",
        "count": 1
      },
      "payment_item": {
        "item": "minecraft:emerald",
        "count": 15
      },
      "secondary_payment_item": {
        "item": "minecraft:potion",
        "count": 1,
        "nbt": "{Potion:\"minecraft:awkward\"}"
      },
      "price_multiplier": 0.5,
      "max_trades": 8,
      "merchant_experience": 9,
      "player_experience": 200,
      "potion": "goblintraders:dig_speed"
    },
    {
      "type": "goblintraders:upgraded_potion",
      "offer_item": {
        "item": "minecraft:potion",
        "count": 1
      },
      "payment_item": {
        "item": "minecraft:emerald",
        "count": 15
      },
      "secondary_payment_item": {
        "item": "minecraft:potion",
        "count": 1,
        "nbt": "{Potion:\"minecraft:awkward\"}"
      },
      "price_multiplier": 0.5,
      "max_trades": 8,
      "merchant_experience": 9,
      "player_experience": 200,
      "potion": "goblintraders:absorption"
    },
    {
      "type": "goblintraders:upgraded_potion",
      "offer_item": {
        "item": "minecraft:potion",
        "count": 1
      },
      "payment_item": {
        "item": "minecraft:emerald",
        "count": 15
      },
      "secondary_payment_item": {
        "item": "minecraft:potion",
        "count": 1,
        "nbt": "{Potion:\"minecraft:awkward\"}"
      },
      "price_multiplier": 0.5,
      "max_trades": 8,
      "merchant_experience": 9,
      "player_experience": 200,
      "potion": "minecraft:luck"
    },
    {
      "type": "goblintraders:upgraded_potion",
      "offer_item": {
        "item": "minecraft:potion",
        "count": 1
      },
      "payment_item": {
        "item": "minecraft:emerald",
        "count": 15
      },
      "secondary_payment_item": {
        "item": "minecraft:potion",
        "count": 1,
        "nbt": "{Potion:\"minecraft:awkward\"}"
      },
      "price_multiplier": 0.5,
      "max_trades": 8,
      "merchant_experience": 9,
      "player_experience": 200,
      "potion": "goblintraders:dolphins_grace"
    },
    {
      "type": "goblintraders:upgraded_potion",
      "offer_item": {
        "item": "minecraft:potion",
        "count": 1
      },
      "payment_item": {
        "item": "minecraft:emerald",
        "count": 15
      },
      "secondary_payment_item": {
        "item": "minecraft:potion",
        "count": 1,
        "nbt": "{Potion:\"minecraft:awkward\"}"
      },
      "price_multiplier": 0.5,
      "max_trades": 8,
      "merchant_experience": 9,
      "player_experience": 200,
      "potion": "goblintraders:levitation"
    },
    {
      "type": "goblintraders:upgraded_potion",
      "offer_item": {
        "item": "minecraft:potion",
        "count": 1
      },
      "payment_item": {
        "item": "minecraft:emerald",
        "count": 15
      },
      "secondary_payment_item": {
        "item": "minecraft:potion",
        "count": 1,
        "nbt": "{Potion:\"minecraft:awkward\"}"
      },
      "price_multiplier": 0.5,
      "max_trades": 8,
      "merchant_experience": 9,
      "player_experience": 200,
      "potion": "minecraft:strong_strength"
    },
    {
      "type": "goblintraders:upgraded_potion",
      "offer_item": {
        "item": "minecraft:potion",
        "count": 1
      },
      "payment_item": {
        "item": "minecraft:emerald",
        "count": 15
      },
      "secondary_payment_item": {
        "item": "minecraft:potion",
        "count": 1,
        "nbt": "{Potion:\"minecraft:awkward\"}"
      },
      "price_multiplier": 0.5,
      "max_trades": 8,
      "merchant_experience": 9,
      "player_experience": 200,
      "potion": "goblintraders:blindness"
    }
  ]
}